toppy/__init__.py
toppy/__main__.py
toppy/client.py
toppy/server.py
toppy/errors/__init__.py
toppy/models/__init__.py
toppy/models/user.py
toppy/models/webhooks.py
toppy/models/widget.py
toppy/ratelimiter/__init__.py
toppy/ratelimiter/bucket.py
top.py-1.4.3.dist-info/LICENSE
top.py-1.4.3.dist-info/METADATA
top.py-1.4.3.dist-info/WHEEL
top.py-1.4.3.dist-info/top_level.txt
top.py-1.4.3.dist-info/RECORD
