Metadata-Version: 2.1
Name: top.py
Version: 1.4.3
Summary: A new, modern API wrapper for the top.gg API
Home-page: https://github.com/dragdev-studios/top.py
Author: EEKIM10
Author-email: eek@clicksminuteper.net
Project-URL: Bug Tracker, https://github.com/dragdev-studios/top.py/issues
Project-URL: Documentation, https://toppy.readthedocs.io/
Project-URL: Source, https://github.com/dragdev-studios/top.py
Classifier: Intended Audience :: Developers
Classifier: Natural Language :: English
Classifier: Operating System :: OS Independent
Classifier: License :: OSI Approved :: MIT License
Classifier: Programming Language :: Python :: 3.6
Classifier: Programming Language :: Python :: 3.7
Classifier: Programming Language :: Python :: 3.8
Classifier: Programming Language :: Python :: 3.9
Classifier: Programming Language :: Python :: 3.10
Classifier: Topic :: Internet
Classifier: Topic :: Software Development :: Libraries
Classifier: Topic :: Software Development :: Libraries :: Python Modules
Classifier: Topic :: Utilities
Classifier: Development Status :: 5 - Production/Stable
Requires-Python: >=3.6
License-File: LICENSE
Provides-Extra: docs
Requires-Dist: sphinx ; extra == 'docs'
Requires-Dist: sphinx-rtd-dark-mode ; extra == 'docs'
Provides-Extra: tests
Requires-Dist: pytest ; extra == 'tests'
